pytorch_image_generation_metrics/__init__.py
pytorch_image_generation_metrics/calc.py
pytorch_image_generation_metrics/calc_fid_stats.py
pytorch_image_generation_metrics/calc_fid_stats_ddp.py
pytorch_image_generation_metrics/calc_metrics.py
pytorch_image_generation_metrics/calc_metrics_ddp.py
pytorch_image_generation_metrics/core.py
pytorch_image_generation_metrics/districuted.py
pytorch_image_generation_metrics/fid_ref.py
pytorch_image_generation_metrics/inception.py
pytorch_image_generation_metrics/utils.py
pytorch_image_generation_metrics/version.py
pytorch_image_generation_metrics-0.6.1.dist-info/LICENSE
pytorch_image_generation_metrics-0.6.1.dist-info/METADATA
pytorch_image_generation_metrics-0.6.1.dist-info/WHEEL
pytorch_image_generation_metrics-0.6.1.dist-info/top_level.txt
pytorch_image_generation_metrics-0.6.1.dist-info/RECORD
