Metadata-Version: 2.1
Name: pytorch-image-generation-metrics
Version: 0.6.1
Summary: Package for calculating image generation metrics using Pytorch
Home-page: https://github.com/w86763777/pytorch_image_generation_metrics
Author: Yi-Lun Wu
Author-email: w86763777@gmail.com
License: UNKNOWN
Keywords: PyTorch,Inception Score,IS,Frechet Inception Distance,FID
Platform: UNKNOWN
Classifier: Programming Language :: Python :: 3
Classifier: License :: OSI Approved :: Apache Software License
Classifier: Operating System :: OS Independent
Requires-Python: >=3.6
License-File: LICENSE
Requires-Dist: pytorch-image-generation-metrics
